{
  "version": "2.2.4",
  "songName": "Tutorial",
  "artist": "Kawai Sprite",
  "charter": "ninjamuffin99 + MtH",
  "offsets": {},
  "playData": {
    "difficulties": ["easy", "normal", "hard"],
    "characters": {
      "player": "bf",
      "opponent": "gf",
      "opponentVocals": ["gf"],
      "playerVocals": ["bf"]
    },
    "stage": "mainStage",
    "noteStyle": "funkin",
    "stickerPack": "bonus-tutorial",
    "ratings": { "easy": 0, "normal": 0, "hard": 1 },
    "album": "volume1"
  },
  "generatedBy": "Friday Night Funkin' - v0.8.1",
  "timeChanges": [{ "t": 0, "b": 0, "bpm": 100, "bt": [4, 4, 4, 4] }]
}
